{
    "id": 143866568,
    "name": "silentCircles of Dex",
    "author": "GGBOBR",
    "creators": [],
    "verifier": "GGBOBR",
    "verification": "https://t.me/CHALLENGE_GRIND/114/3230",
    "percentToQualify": 100,
    "password": "Not Copyable",
    "records": [
        {
            "user": "GGBOBR",
            "link": "",
            "percent": 100,
            "hz": 360
        },
        {
            "user": "LevkaLevka",
            "link": "",
            "percent": 100,
            "hz": 360
        },
        {
            "user": "ItzTheRealMint",
            "link": "https://t.me/CHALLENGE_GRIND/114/3230",
            "percent": 100,
            "hz": 360
        },
        {
            "user": "KillerClean",
            "link": "",
            "percent": 100,
            "hz": 360
        },
        {
            "user": "Triscis",
            "link": "https://t.me/CHALLENGE_GRIND/90629/98503",
            "percent": 100,
            "hz": 360
        },
        {
            "user": "TiraWu3",
            "link": "https://t.me/CHALLENGE_GRIND/90629/103461",
            "percent": 100,
            "hz": 360
        },
        {
            "user": "qropo",
            "link": "https://t.me/CHALLENGE_GRIND/90629/103576",
            "percent": 100,
            "hz": 360
        },
        {
            "user": "kunakov",
            "link": "https://t.me/CHALLENGE_GRIND/90629/103647",
            "percent": 100,
            "hz": 360
        },
        {
            "user": "LTweQuQ",
            "link": "https://t.me/CHALLENGE_GRIND/90629/103670",
            "percent": 100,
            "hz": 360
        }
    ]
}
